cmdformatter/__init__.py
cmdformatter/cmdformatter.py
CMDFormatter-0.1.3.dist-info/METADATA
CMDFormatter-0.1.3.dist-info/WHEEL
CMDFormatter-0.1.3.dist-info/top_level.txt
CMDFormatter-0.1.3.dist-info/RECORD
