Metadata-Version: 2.1
Name: CMDFormatter
Version: 0.1.3
Summary: Package to style and format cmd print
Author: NeuralNine (Florian Dedov)
Author-email: <vishalkrsinghmsk@gmail.com>
Keywords: python,cmd,terminal,styling,user-experience,powershell
Classifier: Development Status :: 1 - Planning
Classifier: Intended Audience :: Developers
Classifier: Programming Language :: Python :: 3
Classifier: Operating System :: Unix
Classifier: Operating System :: MacOS :: MacOS X
Classifier: Operating System :: Microsoft :: Windows
